rainrunoff/__init__.py
rainrunoff/config.py
rainrunoff/logger.py
rainrunoff/main.py
rainrunoff/subbasin.py
rainrunoff/cn_tools/__init__.py
rainrunoff/cn_tools/estimate_cn.py
rainrunoff/io/__init__.py
rainrunoff/io/reader.py
rainrunoff/io/writer.py
rainrunoff/routing/__init__.py
rainrunoff/routing/kinematic.py
rainrunoff/routing/kirpich.py
rainrunoff/routing/muskingum.py
rainrunoff/runoff/__init__.py
rainrunoff/runoff/scs.py
rainrunoff/runoff/water_balance.py
rainrunoff/utils/__init__.py
rainrunoff/utils/date_utils.py
rainrunoff/utils/missing_data.py
rainrunoff/utils/plotting.py
rainrunoff-0.0.1.dist-info/LICENSE
rainrunoff-0.0.1.dist-info/METADATA
rainrunoff-0.0.1.dist-info/WHEEL
rainrunoff-0.0.1.dist-info/top_level.txt
rainrunoff-0.0.1.dist-info/RECORD
